aiowiserbyfeller/__init__.py
aiowiserbyfeller/api.py
aiowiserbyfeller/auth.py
aiowiserbyfeller/const.py
aiowiserbyfeller/enum.py
aiowiserbyfeller/errors.py
aiowiserbyfeller/map.py
aiowiserbyfeller/util.py
aiowiserbyfeller/device/__init__.py
aiowiserbyfeller/device/device.py
aiowiserbyfeller/hvac/__init__.py
aiowiserbyfeller/hvac/hvac.py
aiowiserbyfeller/job/__init__.py
aiowiserbyfeller/job/job.py
aiowiserbyfeller/load/__init__.py
aiowiserbyfeller/load/dali.py
aiowiserbyfeller/load/dali_rgbw.py
aiowiserbyfeller/load/dali_tw.py
aiowiserbyfeller/load/dim.py
aiowiserbyfeller/load/hvac.py
aiowiserbyfeller/load/load.py
aiowiserbyfeller/load/motor.py
aiowiserbyfeller/load/on_off.py
aiowiserbyfeller/scene/__init__.py
aiowiserbyfeller/scene/scene.py
aiowiserbyfeller/sensor/__init__.py
aiowiserbyfeller/sensor/brightness.py
aiowiserbyfeller/sensor/hail.py
aiowiserbyfeller/sensor/rain.py
aiowiserbyfeller/sensor/sensor.py
aiowiserbyfeller/sensor/temperature.py
aiowiserbyfeller/sensor/wind.py
aiowiserbyfeller/smart_button/__init__.py
aiowiserbyfeller/smart_button/smart_button.py
aiowiserbyfeller/system/__init__.py
aiowiserbyfeller/system/condition.py
aiowiserbyfeller/system/flag.py
aiowiserbyfeller/time/__init__.py
aiowiserbyfeller/time/ntp_config.py
aiowiserbyfeller/timer/__init__.py
aiowiserbyfeller/timer/timer.py
aiowiserbyfeller/websocket/__init__.py
aiowiserbyfeller/websocket/websocket.py
aiowiserbyfeller-1.0.0.dist-info/licenses/LICENSE
aiowiserbyfeller-1.0.0.dist-info/METADATA
aiowiserbyfeller-1.0.0.dist-info/WHEEL
aiowiserbyfeller-1.0.0.dist-info/top_level.txt
aiowiserbyfeller-1.0.0.dist-info/RECORD
